wordsapi/__init__.py
wordsapi/api_helper.py
wordsapi/configuration.py
wordsapi/wordsapi_client.py
wordsapi/controllers/__init__.py
wordsapi/controllers/ap_is_controller.py
wordsapi/controllers/base_controller.py
wordsapi/exceptions/__init__.py
wordsapi/exceptions/api_exception.py
wordsapi/http/__init__.py
wordsapi/http/http_call_back.py
wordsapi/http/http_method_enum.py
wordsapi/http/http_request.py
wordsapi/http/http_response.py
wordsapi/http/auth/__init__.py
wordsapi/http/auth/custom_header_authentication.py
wordsapi/models/__init__.py
wordsapi/models/definitions_response.py
wordsapi/models/examples_response.py
wordsapi/models/frequency_details.py
wordsapi/models/frequency_response.py
wordsapi/models/pronunciation_details.py
wordsapi/models/pronunciation_response.py
wordsapi/models/syllable_details.py
wordsapi/models/synonyms_response.py
wordsapi/models/word_details.py
wordsapi/models/word_response.py
wordsapi/utilities/__init__.py
wordsapi/utilities/file_wrapper.py
words_api_client-1.0.2.dist-info/LICENSE
words_api_client-1.0.2.dist-info/METADATA
words_api_client-1.0.2.dist-info/WHEEL
words_api_client-1.0.2.dist-info/top_level.txt
words_api_client-1.0.2.dist-info/RECORD
